HISTORY.md
MANIFEST.in
README.md
UNLICENSE
setup.py
righteous/__init__.py
righteous/cli.py
righteous/compat.py
righteous/config.py
righteous/util.py
righteous.egg-info/PKG-INFO
righteous.egg-info/SOURCES.txt
righteous.egg-info/dependency_links.txt
righteous.egg-info/entry_points.txt
righteous.egg-info/requires.txt
righteous.egg-info/top_level.txt
righteous/api/__init__.py
righteous/api/base.py
righteous/api/deployment.py
righteous/api/server.py
righteous/api/server_template.py